rate_limiter_df/__init__.py
rate_limiter_df/__main__.py
rate_limiter_df/py.typed
rate_limiter_df/rate_limiter.py
rate_limiter_df-0.1.0.dist-info/licenses/LICENSE.txt
rate_limiter_df-0.1.0.dist-info/METADATA
rate_limiter_df-0.1.0.dist-info/WHEEL
rate_limiter_df-0.1.0.dist-info/top_level.txt
rate_limiter_df-0.1.0.dist-info/RECORD
