Metadata-Version: 2.4
Name: rate-limiter-df
Version: 0.1.0
Summary: A decorator-based rate limiter using the token bucket algorithm
Author: Dan Foster
Maintainer: Dan Foster
License: Copyright 2025 Daniel Foster
Project-URL: Homepage, https://github.com/yourusername/rate-limiter-df
Project-URL: Repository, https://github.com/yourusername/rate-limiter-df
Keywords: RateLimiter,Rate,Limiter
Classifier: Development Status :: 3 - Alpha
Classifier: Intended Audience :: Developers
Classifier: License :: OSI Approved :: MIT License
Classifier: Programming Language :: Python :: 3
Classifier: Programming Language :: Python :: 3.7
Classifier: Programming Language :: Python :: 3.8
Classifier: Programming Language :: Python :: 3.9
Classifier: Programming Language :: Python :: 3.10
Classifier: Programming Language :: Python :: 3.11
Classifier: Programming Language :: Python :: 3.12
Requires-Python: >=3.7
License-File: LICENSE.txt
Provides-Extra: dev
Requires-Dist: mypy; extra == "dev"
Requires-Dist: ruff; extra == "dev"
Requires-Dist: pytest; extra == "dev"
Dynamic: license-file
